lison_technology/__init__.py
lison_technology-0.1.0.dist-info/LICENSE
lison_technology-0.1.0.dist-info/METADATA
lison_technology-0.1.0.dist-info/WHEEL
lison_technology-0.1.0.dist-info/top_level.txt
lison_technology-0.1.0.dist-info/RECORD
